README.txt
setup.py
Flipkart.egg-info/PKG-INFO
Flipkart.egg-info/SOURCES.txt
Flipkart.egg-info/dependency_links.txt
Flipkart.egg-info/requires.txt
Flipkart.egg-info/top_level.txt
fk/Flipkart.py
fk/__init__.py