Metadata-Version: 1.1
Name: Flipkart
Version: 1.0
Summary: Flipkart python book search API
Home-page: https://code.google.com/p/flipkart-books-python-api/wiki/README
Author: Vengadanathan Srinivasan
Author-email: fantastic.next@gmail.com
License: BSD
Keywords: Flipkart python book search API
Platform: UNKNOWN
Classifier: Development Status :: 3 - Alpha
Classifier: Topic :: Internet :: WWW/HTTP :: Dynamic Content
Classifier: License :: OSI Approved :: BSD License
Classifier: Operating System :: Microsoft
Classifier: Operating System :: POSIX :: Linux
Classifier: Operating System :: MacOS
